odoo9_addon_cms_form-9.0.1.0.0-py2.7-nspkg.pth
odoo9_addon_cms_form-9.0.1.0.0.dist-info/DESCRIPTION.rst
odoo9_addon_cms_form-9.0.1.0.0.dist-info/METADATA
odoo9_addon_cms_form-9.0.1.0.0.dist-info/RECORD
odoo9_addon_cms_form-9.0.1.0.0.dist-info/WHEEL
odoo9_addon_cms_form-9.0.1.0.0.dist-info/metadata.json
odoo9_addon_cms_form-9.0.1.0.0.dist-info/namespace_packages.txt
odoo9_addon_cms_form-9.0.1.0.0.dist-info/top_level.txt
odoo_addons/cms_form/README.rst
odoo_addons/cms_form/__init__.py
odoo_addons/cms_form/__openerp__.py
odoo_addons/cms_form/utils.py
odoo_addons/cms_form/controllers/__init__.py
odoo_addons/cms_form/controllers/main.py
odoo_addons/cms_form/i18n/de.po
odoo_addons/cms_form/images/cms_form_example_create_partner.png
odoo_addons/cms_form/images/cms_form_example_edit_partner.png
odoo_addons/cms_form/images/cms_form_example_search.png
odoo_addons/cms_form/models/__init__.py
odoo_addons/cms_form/models/cms_form.py
odoo_addons/cms_form/models/cms_form_mixin.py
odoo_addons/cms_form/models/cms_search_form.py
odoo_addons/cms_form/models/test_models.py
odoo_addons/cms_form/models/website_mixin.py
odoo_addons/cms_form/models/widgets.py
odoo_addons/cms_form/security/cms_form.xml
odoo_addons/cms_form/static/description/icon.png
odoo_addons/cms_form/static/src/js/date_widget.js
odoo_addons/cms_form/static/src/js/master_slave.js
odoo_addons/cms_form/static/src/js/select2widgets.js
odoo_addons/cms_form/static/src/js/textarea_widget.js
odoo_addons/cms_form/static/src/less/cms_form.less
odoo_addons/cms_form/templates/assets.xml
odoo_addons/cms_form/templates/form.xml
odoo_addons/cms_form/templates/widgets.xml
odoo_addons/cms_form/tests/__init__.py
odoo_addons/cms_form/tests/common.py
odoo_addons/cms_form/tests/test_controllers.py
odoo_addons/cms_form/tests/test_extractors.py
odoo_addons/cms_form/tests/test_form_base.py
odoo_addons/cms_form/tests/test_form_cms.py
odoo_addons/cms_form/tests/test_form_render.py
odoo_addons/cms_form/tests/test_form_search.py
odoo_addons/cms_form/tests/test_loaders.py
odoo_addons/cms_form/tests/test_widgets.py
