Metadata-Version: 2.0
Name: odoo9-addon-cms-form
Version: 9.0.1.0.0
Summary: Basic content type form
Home-page: UNKNOWN
Author: Camptocamp SA, Odoo Community Association (OCA)
Author-email: support@odoo-community.org
License: LGPL-3
Platform: UNKNOWN
Classifier: Programming Language :: Python :: 2.7
Classifier: Framework :: Odoo
Classifier: License :: OSI Approved :: GNU Lesser General Public License v3 (LGPLv3)
Requires-Dist: odoo (<9.1a,>=9.0a)
Requires-Dist: odoo9-addon-cms-status-message
